suncasa/__init__.py
suncasa/QTeovsa_imager/eovsa_imager.py
suncasa/QTeovsa_imager/fitsutils.py
suncasa/QTeovsa_imager/helioim2fits.py
suncasa/QTeovsa_imager/pr_summary.py
suncasa/QTeovsa_imager/icons/down_right.png
suncasa/QTeovsa_imager/icons/up_left.png
suncasa/dspec/__init__.py
suncasa/dspec/dspec.py
suncasa/dspec/sources/__init__.py
suncasa/dspec/sources/eovsa.py
suncasa/dspec/sources/lwa.py
suncasa/eovsa/__init__.py
suncasa/eovsa/concateovsa.py
suncasa/eovsa/eovsa_IDBfiledownloader.py
suncasa/eovsa/eovsa_diskmodel.py
suncasa/eovsa/eovsa_dspec.py
suncasa/eovsa/eovsa_fitsutils.py
suncasa/eovsa/eovsa_flare_calib.py
suncasa/eovsa/eovsa_flare_pipeline.py
suncasa/eovsa/eovsa_pipeline.py
suncasa/eovsa/eovsa_pipelineAlldayFits.py
suncasa/eovsa/eovsa_pltQlookImage.py
suncasa/eovsa/eovsa_pltQlookMovie.py
suncasa/eovsa/eovsa_readfits.py
suncasa/eovsa/eovsa_scaling.py
suncasa/eovsa/impteovsa.py
suncasa/eovsa/msUtils.py
suncasa/io/__init__.py
suncasa/io/ndfits.py
suncasa/suncasatasks/__init__.py
suncasa/suncasatasks/buildsuncasatasks.py
suncasa/suncasatasks/calibeovsa.py
suncasa/suncasatasks/calibeovsa.xml
suncasa/suncasatasks/concateovsa.py
suncasa/suncasatasks/concateovsa.xml
suncasa/suncasatasks/importeovsa.py
suncasa/suncasatasks/importeovsa.xml
suncasa/suncasatasks/pimfit.py
suncasa/suncasatasks/pimfit.xml
suncasa/suncasatasks/pmaxfit.py
suncasa/suncasatasks/pmaxfit.xml
suncasa/suncasatasks/ptclean.py
suncasa/suncasatasks/ptclean.xml
suncasa/suncasatasks/ptclean6.py
suncasa/suncasatasks/ptclean6.xml
suncasa/suncasatasks/signalsmooth.py
suncasa/suncasatasks/subvs.py
suncasa/suncasatasks/subvs.xml
suncasa/suncasatasks/gotasks/calibeovsa.py
suncasa/suncasatasks/gotasks/concateovsa.py
suncasa/suncasatasks/gotasks/importeovsa.py
suncasa/suncasatasks/gotasks/pimfit.py
suncasa/suncasatasks/gotasks/pmaxfit.py
suncasa/suncasatasks/gotasks/ptclean.py
suncasa/suncasatasks/gotasks/ptclean6.py
suncasa/suncasatasks/gotasks/subvs.py
suncasa/suncasatasks/private/__init__.py
suncasa-1.0.5.dist-info/LICENSE.rst
suncasa-1.0.5.dist-info/METADATA
suncasa-1.0.5.dist-info/WHEEL
suncasa-1.0.5.dist-info/top_level.txt
suncasa-1.0.5.dist-info/RECORD
